pretty_numbers/__init__.py
pretty_numbers/pretty_numbers.py
pretty_numbers/py.typed
prettynumbers-0.3.15.dist-info/LICENSE.txt
prettynumbers-0.3.15.dist-info/METADATA
prettynumbers-0.3.15.dist-info/WHEEL
prettynumbers-0.3.15.dist-info/RECORD
