Metadata-Version: 2.1
Name: prettynumbers
Version: 0.3.15
Summary: Display a range of numbers in a human readable way
Home-page: https://github.com/vfxGer/pretty-numbers
License: GNU GENERAL PUBLIC LICENSE
Author: gerardk
Author-email: gerardk@gmail.com
Requires-Python: >=3.8.0,<4.0.0
Classifier: License :: Other/Proprietary License
Classifier: Programming Language :: Python :: 3
Classifier: Programming Language :: Python :: 3.8
Classifier: Programming Language :: Python :: 3.9
Classifier: Programming Language :: Python :: 3.10
Classifier: Programming Language :: Python :: 3.11
Project-URL: Repository, https://github.com/vfxGer/pretty-numbers
